iso8601/__init__.py
iso8601/formatter.py
iso8601/parser.py
iso_8601-0.3.1.dist-info/METADATA
iso_8601-0.3.1.dist-info/WHEEL
iso_8601-0.3.1.dist-info/RECORD
