Metadata-Version: 2.1
Name: iso-8601
Version: 0.3.1
Summary: Flexible ISO 8601 parser: pass in a valid ISO 8601 string, and a datetime object will be returned.
License: BSD License
Author: Matthew Schinckel
Author-email: matt@schinckel.net
Requires-Python: >=3.9
Classifier: License :: Other/Proprietary License
Classifier: Programming Language :: Python :: 3
Classifier: Programming Language :: Python :: 3.9
Classifier: Programming Language :: Python :: 3.10
Classifier: Programming Language :: Python :: 3.11
Classifier: Programming Language :: Python :: 3.12
Requires-Dist: pytz (==2023.3)
